amnis/__init__.py
amnis/stream.py
amnis-0.2.3.dist-info/LICENSE
amnis-0.2.3.dist-info/METADATA
amnis-0.2.3.dist-info/WHEEL
amnis-0.2.3.dist-info/top_level.txt
amnis-0.2.3.dist-info/RECORD
