Metadata-Version: 2.1
Name: amnis
Version: 0.2.3
Summary: Java like Stream Api for Python
Home-page: https://github.com/zahash/amnis
Author: zahash
Author-email: zahash.z@gmail.com
License: MIT
Classifier: License :: OSI Approved :: MIT License
Classifier: Programming Language :: Python :: 3
Requires-Python: >=3.7
License-File: LICENSE
